CHANGES.rst
MANIFEST.in
README.rst
setup.py
Kate_plugins.egg-info/PKG-INFO
Kate_plugins.egg-info/SOURCES.txt
Kate_plugins.egg-info/dependency_links.txt
Kate_plugins.egg-info/not-zip-safe
Kate_plugins.egg-info/requires.txt
Kate_plugins.egg-info/top_level.txt
kate_plugins/__init__.py
kate_plugins/autopate.py
kate_plugins/kate_core_plugins.py
kate_plugins/kate_plugins.py
kate_plugins/kate_settings_plugins.py
kate_plugins/jste_plugins/__init__.py
kate_plugins/jste_plugins/autocomplete.py
kate_plugins/jste_plugins/autocomplete_jquery.json
kate_plugins/jste_plugins/autocomplete_jquery.json.gen
kate_plugins/jste_plugins/autocomplete_js.json
kate_plugins/jste_plugins/jquery_plugins.py
kate_plugins/jste_plugins/jslint_plugins.py
kate_plugins/jste_plugins/json_plugins.py
kate_plugins/pyte_plugins/__init__.py
kate_plugins/pyte_plugins/text_plugins.py
kate_plugins/pyte_plugins/autocomplete/__init__.py
kate_plugins/pyte_plugins/autocomplete/autocomplete.py
kate_plugins/pyte_plugins/autocomplete/parse.py
kate_plugins/pyte_plugins/check_plugins/__init__.py
kate_plugins/pyte_plugins/check_plugins/check_all_plugins.py
kate_plugins/pyte_plugins/check_plugins/commons.py
kate_plugins/pyte_plugins/check_plugins/parse_plugins.py
kate_plugins/pyte_plugins/check_plugins/pep8_plugins.py
kate_plugins/pyte_plugins/check_plugins/pyflakes_plugins.py
kate_plugins/pyte_plugins/djte_plugins/__init__.py
kate_plugins/pyte_plugins/djte_plugins/block_plugins.py
kate_plugins/pyte_plugins/djte_plugins/class_plugins.py
kate_plugins/pyte_plugins/djte_plugins/text_plugins.py
kate_plugins/xhtml_plugins/__init__.py
kate_plugins/xhtml_plugins/xml_plugins.py