Metadata-Version: 1.1
Name: Kate-plugins
Version: 0.2.2
Summary: Plugins to Kate editor to develop faster python projects, django projects and something of javascript
Home-page: https://github.com/goinnn/Kate-plugins
Author: Pablo Martin
Author-email: goinnn@gmail.com
License: GNU Lesser General Public License
Keywords: kate,pate,plugins,kate plugins,pate plugins,python,autocomplete,autocomplete python,django,jquery,js,checker,pep8,pyflakes,jslint
Platform: UNKNOWN
Classifier: Development Status :: 4 - Beta
Classifier: Environment :: Plugins
Classifier: Intended Audience :: Developers
Classifier: Natural Language :: English
Classifier: Programming Language :: Python :: 2.6
Classifier: Topic :: Software Development
